odoo8_addon_web_onchange_action-8.0.1.0.0.99.dev2-py2.7-nspkg.pth
odoo8_addon_web_onchange_action-8.0.1.0.0.99.dev2.dist-info/DESCRIPTION.rst
odoo8_addon_web_onchange_action-8.0.1.0.0.99.dev2.dist-info/METADATA
odoo8_addon_web_onchange_action-8.0.1.0.0.99.dev2.dist-info/RECORD
odoo8_addon_web_onchange_action-8.0.1.0.0.99.dev2.dist-info/WHEEL
odoo8_addon_web_onchange_action-8.0.1.0.0.99.dev2.dist-info/metadata.json
odoo8_addon_web_onchange_action-8.0.1.0.0.99.dev2.dist-info/namespace_packages.txt
odoo8_addon_web_onchange_action-8.0.1.0.0.99.dev2.dist-info/top_level.txt
odoo_addons/web_onchange_action/README.rst
odoo_addons/web_onchange_action/__init__.py
odoo_addons/web_onchange_action/__openerp__.py
odoo_addons/web_onchange_action/i18n/web_onchange_action.pot
odoo_addons/web_onchange_action/static/description/icon.png
odoo_addons/web_onchange_action/static/src/css/web_onchange_action.css
odoo_addons/web_onchange_action/static/src/js/web_onchange_action.js
odoo_addons/web_onchange_action/views/templates.xml
